plyable/__init__.py
plyable/app.py
plyable/helpers.py
plyable/plyable.py
plyable/lib/__init__.py
plyable/lib/helpers.py
plyable-0.0.4.dist-info/LICENSE.md
plyable-0.0.4.dist-info/METADATA
plyable-0.0.4.dist-info/WHEEL
plyable-0.0.4.dist-info/top_level.txt
plyable-0.0.4.dist-info/RECORD
