Metadata-Version: 2.1
Name: plyable
Version: 0.0.4
Summary: A Microframework for working with LLMs
Author: Christine Kinniburgh
Author-email: Christine Kinniburgh <pip@cjkinni.com>
License: AGPLv3
Project-URL: Homepage, https://github.com/cjkinni/plyable
Project-URL: Bug Tracker, https://github.com/cjkinni/plyable/issues
Keywords: llm openai chatgpt gpt3 gpt4 gpt-3 gpt-4
Classifier: Development Status :: 3 - Alpha
Classifier: Intended Audience :: Developers
Classifier: License :: OSI Approved :: GNU General Public License v3 (GPLv3)
Classifier: Programming Language :: Python :: 3
Requires-Python: >=3.7
License-File: LICENSE.md
Requires-Dist: openai (>=0.10.0)
